pydantic_snowflake/__init__.py
pydantic_snowflake/const.py
pydantic_snowflake/generator.py
pydantic_snowflake/snowflake.py
pydantic_snowflake-0.1.2.dist-info/METADATA
pydantic_snowflake-0.1.2.dist-info/WHEEL
pydantic_snowflake-0.1.2.dist-info/licenses/LICENSE
pydantic_snowflake-0.1.2.dist-info/RECORD
