Metadata-Version: 2.4
Name: pydantic-snowflake
Version: 0.1.2
Summary: A Pydantic custom type for handling Snowflake IDs with ease.
Project-URL: Homepage, https://github.com/zhihao1021/pydantic_snowflake
Project-URL: GitHub, https://github.com/zhihao1021/pydantic_snowflake
Project-URL: Bug, https://github.com/zhihao1021/pydantic_snowflake/issues
Project-URL: Changelog, https://github.com/zhihao1021/pydantic_snowflake/blob/main/CHANGELOG.md
Author-email: Chih-Hao Chuang <contact@chih-hao.xyz>
License-Expression: MIT
License-File: LICENSE
Keywords: custom type,data validation,pydantic,snowflake
Classifier: Development Status :: 5 - Production/Stable
Classifier: Framework :: Pydantic
Classifier: Framework :: Pydantic :: 2
Classifier: Intended Audience :: Developers
Classifier: License :: OSI Approved :: MIT License
Classifier: Operating System :: OS Independent
Classifier: Programming Language :: Python
Classifier: Programming Language :: Python :: 3
Classifier: Programming Language :: Python :: 3 :: Only
Classifier: Programming Language :: Python :: 3.7
Classifier: Programming Language :: Python :: 3.8
Classifier: Programming Language :: Python :: 3.9
Classifier: Programming Language :: Python :: 3.10
Classifier: Programming Language :: Python :: 3.11
Classifier: Programming Language :: Python :: 3.12
Classifier: Programming Language :: Python :: 3.13
Classifier: Programming Language :: Python :: 3.14
Classifier: Programming Language :: Python :: Implementation :: CPython
Classifier: Programming Language :: Python :: Implementation :: PyPy
Classifier: Topic :: Software Development :: Libraries :: Python Modules
Classifier: Typing :: Typed
Requires-Python: >=3.7
Requires-Dist: pydantic>=2.0.0
